CHANGELOG.txt
LICENSE
MANIFEST.in
README.md
setup.py
YSL_H_isaac23.egg-info/PKG-INFO
YSL_H_isaac23.egg-info/SOURCES.txt
YSL_H_isaac23.egg-info/dependency_links.txt
YSL_H_isaac23.egg-info/requires.txt
YSL_H_isaac23.egg-info/top_level.txt
venv/Lib/site-packages/PyQt5/__init__.py
venv/Lib/site-packages/PyQt5/uic/__init__.py
venv/Lib/site-packages/PyQt5/uic/Compiler/__init__.py
venv/Lib/site-packages/PyQt5/uic/Loader/__init__.py
venv/Lib/site-packages/PyQt5/uic/port_v2/__init__.py
venv/Lib/site-packages/PyQt5/uic/port_v3/__init__.py
venv/Lib/site-packages/Pygments-2.8.0.dist-info/LICENSE
venv/Lib/site-packages/_distutils_hack/__init__.py
venv/Lib/site-packages/beautifulsoup4-4.9.3.dist-info/LICENSE
venv/Lib/site-packages/bleach/__init__.py
venv/Lib/site-packages/bleach-3.3.0.dist-info/LICENSE
venv/Lib/site-packages/bleach/_vendor/__init__.py
venv/Lib/site-packages/bleach/_vendor/django/__init__.py
venv/Lib/site-packages/bleach/_vendor/django/core/__init__.py
venv/Lib/site-packages/bleach/_vendor/html5lib/__init__.py
venv/Lib/site-packages/bleach/_vendor/html5lib/_trie/__init__.py
venv/Lib/site-packages/bleach/_vendor/html5lib/filters/__init__.py
venv/Lib/site-packages/bleach/_vendor/html5lib/treeadapters/__init__.py
venv/Lib/site-packages/bleach/_vendor/html5lib/treebuilders/__init__.py
venv/Lib/site-packages/bleach/_vendor/html5lib/treewalkers/__init__.py
venv/Lib/site-packages/bs4/__init__.py
venv/Lib/site-packages/bs4/builder/__init__.py
venv/Lib/site-packages/bs4/tests/__init__.py
venv/Lib/site-packages/certifi/__init__.py
venv/Lib/site-packages/certifi-2020.12.5.dist-info/LICENSE
venv/Lib/site-packages/chardet/__init__.py
venv/Lib/site-packages/chardet-4.0.0.dist-info/LICENSE
venv/Lib/site-packages/chardet/cli/__init__.py
venv/Lib/site-packages/chardet/metadata/__init__.py
venv/Lib/site-packages/click/__init__.py
venv/Lib/site-packages/colorama/__init__.py
venv/Lib/site-packages/docutils/__init__.py
venv/Lib/site-packages/docutils/languages/__init__.py
venv/Lib/site-packages/docutils/parsers/__init__.py
venv/Lib/site-packages/docutils/parsers/rst/__init__.py
venv/Lib/site-packages/docutils/parsers/rst/directives/__init__.py
venv/Lib/site-packages/docutils/parsers/rst/languages/__init__.py
venv/Lib/site-packages/docutils/readers/__init__.py
venv/Lib/site-packages/docutils/transforms/__init__.py
venv/Lib/site-packages/docutils/utils/__init__.py
venv/Lib/site-packages/docutils/utils/math/__init__.py
venv/Lib/site-packages/importlib_metadata-3.4.0.dist-info/LICENSE
venv/Lib/site-packages/keyring-22.0.1.dist-info/LICENSE
venv/Lib/site-packages/packaging-20.9.dist-info/LICENSE
venv/Lib/site-packages/pyparsing-2.4.7.dist-info/LICENSE
venv/Lib/site-packages/python_dotenv-0.15.0.dist-info/LICENSE
venv/Lib/site-packages/readme_renderer-28.0.dist-info/LICENSE
venv/Lib/site-packages/requests-2.25.1.dist-info/LICENSE
venv/Lib/site-packages/requests_toolbelt-0.9.1.dist-info/LICENSE
venv/Lib/site-packages/rfc3986-1.4.0.dist-info/LICENSE
venv/Lib/site-packages/selenium-3.141.0.dist-info/LICENSE
venv/Lib/site-packages/setuptools-51.0.0.dist-info/LICENSE
venv/Lib/site-packages/six-1.15.0.dist-info/LICENSE
venv/Lib/site-packages/twine-3.3.0.dist-info/LICENSE
venv/Lib/site-packages/typing_extensions-3.7.4.3.dist-info/LICENSE
venv/Lib/site-packages/zipp-3.4.0.dist-info/LICENSE
