Metadata-Version: 2.1
Name: YSL-H-isaac23
Version: 1.2.0
Summary: A package for automated liking of Active YouTube Streams programmatically using selenium and requests.
Home-page: https://github.com/H-isaac23/Youtube-Streams-Liker
Author: John Isaac Delgado
Author-email: dev.isaac23@gmail.com
License: MIT
Platform: UNKNOWN
Classifier: Programming Language :: Python :: 3
Classifier: License :: OSI Approved :: MIT License
Classifier: Operating System :: OS Independent
Requires-Python: >=3.6
